ratus/__init__.py
ratus/execer.py
ratus/parse.py
ratus/token.py
ratus-0.0.3.dist-info/LICENSE
ratus-0.0.3.dist-info/WHEEL
ratus-0.0.3.dist-info/METADATA
ratus-0.0.3.dist-info/RECORD
