Metadata-Version: 2.1
Name: ratus
Version: 0.0.3
Summary: Simple expression language.
Home-page: https://github.com/nick96/ratus
License: MIT
Keywords: dsl,expression-language
Author: Nick Spain
Author-email: nicholas.spain96@gmail.com
Requires-Python: >=3.7,<4.0
Classifier: Development Status :: 2 - Pre-Alpha
Classifier: License :: OSI Approved :: MIT License
Classifier: Programming Language :: Python :: 3
Classifier: Programming Language :: Python :: 3.7
Classifier: Programming Language :: Python :: 3.8
Project-URL: Repository, https://github.com/nick96/ratus
